Workbook

Sheet Notes
A1: DataStaqAI Financial Model — read me
A3: ILLUSTRATIVE planning case. Edit the yellow cells on 'Assumptions' and the 'Model' sheet recalculates live.
A4: Default case → Ending recurring ARR ~ $4.8M and total revenue ~ $4.6M by Year 3 (exit run-rate in the $5–10M band).
A5: $5–10M is sensitive to THREE levers: new logos x landing ACV x NRR. Two routes get there:
A6: (a) volume route: ~90–95 logos at $40k landing + 35% NRR (the default), or
A7: (b) expansion route: ~50 logos at $40k landing + ~50% NRR (fewer logos, higher net retention).
A8: Gross margin ramps 52%→70% as the reusable agent/connector library matures (the services-to-software trajectory).
A9: COGS is captured inside gross margin %; headcount is shown for revenue/head sanity, not double-counted in EBITDA.
A10: All figures are a model, not a forecast — replace with real win/loss, cost-to-serve and cohort data before external use.
A11: Companion to 'The Agentic Enterprise' deck + report + competitor database.

Sheet Assumptions
A1: DataStaqAI — Financial Model · Assumptions (edit yellow cells; Model recalculates)
A3: Key | B3: Driver | C3: Value | D3: Unit
A4: NRR_annual | B4: Net revenue retention (annual) | C4: 1.35 | D4: x
A5: Landing_ACV | B5: Avg landing ACV (recurring, $/yr) | C5: 40000 | D5: $
A6: GM_Y1 | B6: Gross margin — Year 1 | C6: 0.52 | D6: %
A7: GM_Y2 | B7: Gross margin — Year 2 | C7: 0.62 | D7: %
A8: GM_Y3 | B8: Gross margin — Year 3 | C8: 0.7 | D8: %
A9: Logos_Y1 | B9: New logos — Year 1 | C9: 15 | D9: #
A10: Logos_Y2 | B10: New logos — Year 2 | C10: 35 | D10: #
A11: Logos_Y3 | B11: New logos — Year 3 | C11: 45 | D11: #
A12: Build_fee | B12: Avg BUILD project fee ($) | C12: 80000 | D12: $
A13: Build_Y1 | B13: BUILD projects — Year 1 | C13: 5 | D13: #
A14: Build_Y2 | B14: BUILD projects — Year 2 | C14: 10 | D14: #
A15: Build_Y3 | B15: BUILD projects — Year 3 | C15: 14 | D15: #
... A24: Avg_life_yrs | B24: Avg customer life (yrs, for LTV) | C24: 4 | D24: #

Sheet Model
A1: 3-Year P&L & SaaS metrics (driver-based; edit Assumptions to recalc)
A3: Line | B3: Year 1 | C3: Year 2 | D3: Year 3
A4: New logos | B4: =Assumptions!$C$9 | C4: =Assumptions!$C$10 | D4: =Assumptions!$C$11
A5: Cumulative logos | B5: =B4 | C5: =B5+C4 | D5: =C5+D4
A6: New recurring ARR ($) | B6: =B4*Assumptions!$C$5 | C6: =C4*Assumptions!$C$5 | D6: =D4*Assumptions!$C$5
A7: Beginning recurring ARR ($) | B7: =0 | C7: =B9 | D7: =C9
A8: Expansion ARR ($) | B8: =B7*(Assumptions!$C$4-1) | C8: =C7*(Assumptions!$C$4-1) | D8: =D7*(Assumptions!$C$4-1)
A9: Ending recurring ARR ($) | B9: =B7+B6+B8 | C9: =C7+C6+C8 | D9: =D7+D6+D8
A10: Recurring revenue (recognized, $) | B10: =(B7+B9)/2 | C10: =(C7+C9)/2 | D10: =(D7+D9)/2
A11: BUILD revenue ($) | B11: =Assumptions!$C$13*Assumptions!$C$12 | C11: =Assumptions!$C$14*Assumptions!$C$12 | D11: =Assumptions!$C$15*Assumptions!$C$12
A12: Total revenue ($) | B12: =B10+B11 | C12: =C10+C11 | D12: =D10+D11
A13: Gross margin % | B13: =Assumptions!$C$6 | C13: =Assumptions!$C$7 | D13: =Assumptions!$C$8
A14: Gross profit ($) | B14: =B12*B13 | C14: =C12*C13 | D14: =D12*D13
A15: Opex S&M+G&A ($) | B15: =B12*Assumptions!$C$23 | C15: =C12*Assumptions!$C$23 | D15: =D12*Assumptions!$C$23
A16: EBITDA ($) | B16: =B14-B15 | C16: =C14-C15 | D16: =D14-D15
A17: Delivery pods | B17: =ROUNDUP(B5/Assumptions!$C$16,0) | C17: =ROUNDUP(C5/Assumptions!$C$16,0) | D17: =ROUNDUP(D5/Assumptions!$C$16,0)
A18: Total headcount | B18: =B17*Assumptions!$C$17+Assumptions!$C$19 | C18: =C17*Assumptions!$C$17+Assumptions!$C$20 | D18: =D17*Assumptions!$C$17+Assumptions!$C$21
A19: Revenue / head ($) | B19: =B12/B18 | C19: =C12/C18 | D19: =D12/D18
A20: CAC payback (months) | B20: =Assumptions!$C$22/((Assumptions!$C$5*B13)/12) | C20: =Assumptions!$C$22/((Assumptions!$C$5*C13)/12) | D20: =Assumptions!$C$22/((Assumptions!$C$5*D13)/12)
A21: LTV / CAC (x) | B21: =(Assumptions!$C$5*B13*Assumptions!$C$24)/Assumptions!$C$22 | C21: =(Assumptions!$C$5*C13*Assumptions!$C$24)/Assumptions!$C$22 | D21: =(Assumptions!$C$5*D13*Assumptions!$C$24)/Assumptions!$C$22
